{
  "coord": {
    "lon": 28.0436,
    "lat": -26.2023
  },
  "weather": [
    {
      "id": 803,
      "main": "Clouds",
      "description": "broken clouds",
      "icon": "04d"
    }
  ],
  "base": "stations",
  "main": {
    "temp": 16.04,
    "feels_like": 15.95,
    "temp_min": 16.01,
    "temp_max": 16.06,
    "pressure": 1017,
    "humidity": 86,
    "sea_level": 1017,
    "grnd_level": 832
  },
  "visibility": 10000,
  "wind": {
    "speed": 0.45,
    "deg": 239,
    "gust": 4.02
  },
  "clouds": {
    "all": 59
  },
  "dt": 1765082150,
  "sys": {
    "type": 2,
    "id": 2005686,
    "country": "ZA",
    "sunrise": 1765076881,
    "sunset": 1765126252
  },
  "timezone": 7200,
  "id": 993800,
  "name": "Johannesburg",
  "cod": 200
}