{
  "coord": {
    "lon": -74.006,
    "lat": 40.7143
  },
  "weather": [
    {
      "id": 800,
      "main": "Clear",
      "description": "clear sky",
      "icon": "01n"
    }
  ],
  "base": "stations",
  "main": {
    "temp": -1.5,
    "feels_like": -8.5,
    "temp_min": -2.88,
    "temp_max": -0.81,
    "pressure": 1029,
    "humidity": 50,
    "sea_level": 1029,
    "grnd_level": 1027
  },
  "visibility": 10000,
  "wind": {
    "speed": 9.77,
    "deg": 300,
    "gust": 13.38
  },
  "clouds": {
    "all": 0
  },
  "dt": 1766378522,
  "sys": {
    "type": 1,
    "id": 4610,
    "country": "US",
    "sunrise": 1766319403,
    "sunset": 1766352703
  },
  "timezone": -18000,
  "id": 5128581,
  "name": "New York",
  "cod": 200
}