{
  "coord": {
    "lon": 28.0436,
    "lat": -26.2023
  },
  "weather": [
    {
      "id": 804,
      "main": "Clouds",
      "description": "overcast clouds",
      "icon": "04d"
    }
  ],
  "base": "stations",
  "main": {
    "temp": 13.72,
    "feels_like": 13.26,
    "temp_min": 12.67,
    "temp_max": 13.97,
    "pressure": 1016,
    "humidity": 81,
    "sea_level": 1016,
    "grnd_level": 829
  },
  "visibility": 10000,
  "wind": {
    "speed": 0.45,
    "deg": 226,
    "gust": 3.13
  },
  "clouds": {
    "all": 100
  },
  "dt": 1760243026,
  "sys": {
    "type": 2,
    "id": 2089722,
    "country": "ZA",
    "sunrise": 1760240141,
    "sunset": 1760285557
  },
  "timezone": 7200,
  "id": 993800,
  "name": "Johannesburg",
  "cod": 200
}