{
  "coord": {
    "lon": 28.0436,
    "lat": -26.2023
  },
  "weather": [
    {
      "id": 801,
      "main": "Clouds",
      "description": "few clouds",
      "icon": "02d"
    }
  ],
  "base": "stations",
  "main": {
    "temp": 13.06,
    "feels_like": 12.95,
    "temp_min": 11.56,
    "temp_max": 13.28,
    "pressure": 1017,
    "humidity": 97,
    "sea_level": 1017,
    "grnd_level": 828
  },
  "visibility": 10000,
  "wind": {
    "speed": 5.11,
    "deg": 3,
    "gust": 8.65
  },
  "clouds": {
    "all": 21
  },
  "dt": 1764564638,
  "sys": {
    "type": 2,
    "id": 2005686,
    "country": "ZA",
    "sunrise": 1764558452,
    "sunset": 1764607594
  },
  "timezone": 7200,
  "id": 993800,
  "name": "Johannesburg",
  "cod": 200
}