{
  "coord": {
    "lon": 18.4232,
    "lat": -33.9258
  },
  "weather": [
    {
      "id": 800,
      "main": "Clear",
      "description": "clear sky",
      "icon": "01n"
    }
  ],
  "base": "stations",
  "main": {
    "temp": 8.31,
    "feels_like": 8.31,
    "temp_min": 7.73,
    "temp_max": 11.44,
    "pressure": 1030,
    "humidity": 75,
    "sea_level": 1030,
    "grnd_level": 1028
  },
  "visibility": 10000,
  "wind": {
    "speed": 0.45,
    "deg": 0,
    "gust": 2.24
  },
  "clouds": {
    "all": 0
  },
  "dt": 1752899776,
  "sys": {
    "type": 2,
    "id": 2073005,
    "country": "ZA",
    "sunrise": 1752904037,
    "sunset": 1752940652
  },
  "timezone": 7200,
  "id": 3369157,
  "name": "Cape Town",
  "cod": 200
}