{
  "coord": {
    "lon": 27.7752,
    "lat": -26.0858
  },
  "weather": [
    {
      "id": 800,
      "main": "Clear",
      "description": "clear sky",
      "icon": "01d"
    }
  ],
  "base": "stations",
  "main": {
    "temp": 15.05,
    "feels_like": 14.8,
    "temp_min": 14.68,
    "temp_max": 15.73,
    "pressure": 1019,
    "humidity": 84,
    "sea_level": 1019,
    "grnd_level": 835
  },
  "visibility": 10000,
  "wind": {
    "speed": 3.48,
    "deg": 5,
    "gust": 5.73
  },
  "clouds": {
    "all": 0
  },
  "dt": 1762403513,
  "sys": {
    "type": 2,
    "id": 2008899,
    "country": "ZA",
    "sunrise": 1762398980,
    "sunset": 1762446523
  },
  "timezone": 7200,
  "id": 986822,
  "name": "Krugersdorp",
  "cod": 200
}