{
  "coord": {
    "lon": 26.214,
    "lat": -29.1211
  },
  "weather": [
    {
      "id": 501,
      "main": "Rain",
      "description": "moderate rain",
      "icon": "10d"
    }
  ],
  "base": "stations",
  "main": {
    "temp": 15.71,
    "feels_like": 15.63,
    "temp_min": 15.71,
    "temp_max": 15.71,
    "pressure": 1017,
    "humidity": 88,
    "sea_level": 1017,
    "grnd_level": 865
  },
  "visibility": 5000,
  "wind": {
    "speed": 1.54,
    "deg": 40
  },
  "rain": {
    "1h": 0.15
  },
  "clouds": {
    "all": 100
  },
  "dt": 1762749135,
  "sys": {
    "type": 1,
    "id": 1884,
    "country": "ZA",
    "sunrise": 1762744526,
    "sunset": 1762792968
  },
  "timezone": 7200,
  "id": 1018725,
  "name": "Bloemfontein",
  "cod": 200
}