{
  "coord": {
    "lon": 1.3378,
    "lat": 51.2722
  },
  "weather": [
    {
      "id": 804,
      "main": "Clouds",
      "description": "overcast clouds",
      "icon": "04n"
    }
  ],
  "base": "stations",
  "main": {
    "temp": 8.88,
    "feels_like": 4.54,
    "temp_min": 8.86,
    "temp_max": 10.08,
    "pressure": 1010,
    "humidity": 83,
    "sea_level": 1010,
    "grnd_level": 1007
  },
  "visibility": 10000,
  "wind": {
    "speed": 10.86,
    "deg": 207,
    "gust": 15.74
  },
  "clouds": {
    "all": 100
  },
  "dt": 1764564790,
  "sys": {
    "type": 2,
    "id": 2072746,
    "country": "GB",
    "sunrise": 1764574632,
    "sunset": 1764604236
  },
  "timezone": 0,
  "id": 2638542,
  "name": "Sandwich",
  "cod": 200
}