{
  "coord": {
    "lon": -2.0981,
    "lat": 57.1437
  },
  "weather": [
    {
      "id": 803,
      "main": "Clouds",
      "description": "broken clouds",
      "icon": "04n"
    }
  ],
  "base": "stations",
  "main": {
    "temp": -0.24,
    "feels_like": -2.81,
    "temp_min": -1,
    "temp_max": 0.86,
    "pressure": 1016,
    "humidity": 96,
    "sea_level": 1016,
    "grnd_level": 1010
  },
  "visibility": 10000,
  "wind": {
    "speed": 2.06,
    "deg": 10
  },
  "clouds": {
    "all": 75
  },
  "dt": 1763094586,
  "sys": {
    "type": 1,
    "id": 1440,
    "country": "GB",
    "sunrise": 1763106509,
    "sunset": 1763135844
  },
  "timezone": 0,
  "id": 2657832,
  "name": "Aberdeen",
  "cod": 200
}