{
  "coord": {
    "lon": -2.0981,
    "lat": 57.1437
  },
  "weather": [
    {
      "id": 804,
      "main": "Clouds",
      "description": "overcast clouds",
      "icon": "04n"
    }
  ],
  "base": "stations",
  "main": {
    "temp": 7.3,
    "feels_like": 4.9,
    "temp_min": 6.41,
    "temp_max": 7.33,
    "pressure": 997,
    "humidity": 90,
    "sea_level": 997,
    "grnd_level": 991
  },
  "visibility": 10000,
  "wind": {
    "speed": 3.6,
    "deg": 150
  },
  "clouds": {
    "all": 100
  },
  "dt": 1764822960,
  "sys": {
    "type": 1,
    "id": 1440,
    "country": "GB",
    "sunrise": 1764836862,
    "sunset": 1764862196
  },
  "timezone": 0,
  "id": 2657832,
  "name": "Aberdeen",
  "cod": 200
}