{
  "coord": {
    "lon": 2.3488,
    "lat": 48.8534
  },
  "weather": [
    {
      "id": 804,
      "main": "Clouds",
      "description": "overcast clouds",
      "icon": "04n"
    }
  ],
  "base": "stations",
  "main": {
    "temp": 11.93,
    "feels_like": 11.55,
    "temp_min": 10.77,
    "temp_max": 12.43,
    "pressure": 1013,
    "humidity": 91,
    "sea_level": 1013,
    "grnd_level": 1005
  },
  "visibility": 10000,
  "wind": {
    "speed": 5.14,
    "deg": 230
  },
  "clouds": {
    "all": 100
  },
  "dt": 1761625549,
  "sys": {
    "type": 1,
    "id": 6550,
    "country": "FR",
    "sunrise": 1761633063,
    "sunset": 1761669450
  },
  "timezone": 3600,
  "id": 2988507,
  "name": "Paris",
  "cod": 200
}