{
  "coord": {
    "lon": -0.3833,
    "lat": 52.7667
  },
  "weather": [
    {
      "id": 804,
      "main": "Clouds",
      "description": "overcast clouds",
      "icon": "04n"
    }
  ],
  "base": "stations",
  "main": {
    "temp": 1.75,
    "feels_like": -1.86,
    "temp_min": 1.03,
    "temp_max": 2.72,
    "pressure": 1020,
    "humidity": 88,
    "sea_level": 1020,
    "grnd_level": 1014
  },
  "visibility": 10000,
  "wind": {
    "speed": 3.6,
    "deg": 240
  },
  "clouds": {
    "all": 100
  },
  "dt": 1763440214,
  "sys": {
    "type": 1,
    "id": 1511,
    "country": "GB",
    "sunrise": 1763450993,
    "sunset": 1763481831
  },
  "timezone": 0,
  "id": 2655099,
  "name": "Bourne",
  "cod": 200
}