{
  "coord": {
    "lon": -2.5967,
    "lat": 51.4552
  },
  "weather": [
    {
      "id": 803,
      "main": "Clouds",
      "description": "broken clouds",
      "icon": "04n"
    }
  ],
  "base": "stations",
  "main": {
    "temp": 12.35,
    "feels_like": 12.12,
    "temp_min": 11.91,
    "temp_max": 12.84,
    "pressure": 1004,
    "humidity": 95,
    "sea_level": 1004,
    "grnd_level": 996
  },
  "visibility": 9000,
  "wind": {
    "speed": 4.63,
    "deg": 140
  },
  "clouds": {
    "all": 75
  },
  "dt": 1762489740,
  "sys": {
    "type": 2,
    "id": 2029649,
    "country": "GB",
    "sunrise": 1762499666,
    "sunset": 1762533224
  },
  "timezone": 0,
  "id": 2654675,
  "name": "Bristol",
  "cod": 200
}