{
  "coord": {
    "lon": 9.1895,
    "lat": 45.4643
  },
  "weather": [
    {
      "id": 500,
      "main": "Rain",
      "description": "light rain",
      "icon": "10d"
    }
  ],
  "base": "stations",
  "main": {
    "temp": 18.97,
    "feels_like": 19.09,
    "temp_min": 17.86,
    "temp_max": 19.43,
    "pressure": 1006,
    "humidity": 83,
    "sea_level": 1006,
    "grnd_level": 993
  },
  "visibility": 10000,
  "wind": {
    "speed": 1.54,
    "deg": 330
  },
  "rain": {
    "1h": 0.65
  },
  "clouds": {
    "all": 75
  },
  "dt": 1753678106,
  "sys": {
    "type": 1,
    "id": 6742,
    "country": "IT",
    "sunrise": 1753675354,
    "sunset": 1753729000
  },
  "timezone": 7200,
  "id": 3173435,
  "name": "Milan",
  "cod": 200
}