{
  "coord": {
    "lon": 1.3378,
    "lat": 51.2722
  },
  "weather": [
    {
      "id": 803,
      "main": "Clouds",
      "description": "broken clouds",
      "icon": "04n"
    }
  ],
  "base": "stations",
  "main": {
    "temp": 1.87,
    "feels_like": -2.67,
    "temp_min": 1.18,
    "temp_max": 2.19,
    "pressure": 1031,
    "humidity": 91,
    "sea_level": 1031,
    "grnd_level": 1026
  },
  "visibility": 10000,
  "wind": {
    "speed": 5.17,
    "deg": 333,
    "gust": 8.23
  },
  "clouds": {
    "all": 71
  },
  "dt": 1767156098,
  "sys": {
    "type": 2,
    "id": 2040265,
    "country": "GB",
    "sunrise": 1767167951,
    "sunset": 1767196550
  },
  "timezone": 0,
  "id": 2638542,
  "name": "Sandwich",
  "cod": 200
}