{
  "coord": {
    "lon": 1.3378,
    "lat": 51.2722
  },
  "weather": [
    {
      "id": 803,
      "main": "Clouds",
      "description": "broken clouds",
      "icon": "04d"
    }
  ],
  "base": "stations",
  "main": {
    "temp": 11.29,
    "feels_like": 10.8,
    "temp_min": 10.08,
    "temp_max": 11.74,
    "pressure": 1018,
    "humidity": 89,
    "sea_level": 1018,
    "grnd_level": 1014
  },
  "visibility": 10000,
  "wind": {
    "speed": 3.09,
    "deg": 253,
    "gust": 5.04
  },
  "clouds": {
    "all": 69
  },
  "dt": 1777702366,
  "sys": {
    "type": 2,
    "id": 2072746,
    "country": "GB",
    "sunrise": 1777695935,
    "sunset": 1777749453
  },
  "timezone": 3600,
  "id": 2638542,
  "name": "Sandwich",
  "cod": 200
}