{
  "coord": {
    "lon": 116.3972,
    "lat": 39.9075
  },
  "weather": [
    {
      "id": 500,
      "main": "Rain",
      "description": "light rain",
      "icon": "10d"
    }
  ],
  "base": "stations",
  "main": {
    "temp": 15.21,
    "feels_like": 14.93,
    "temp_min": 15.21,
    "temp_max": 15.21,
    "pressure": 1014,
    "humidity": 82,
    "sea_level": 1014,
    "grnd_level": 1009
  },
  "visibility": 10000,
  "wind": {
    "speed": 4.14,
    "deg": 348,
    "gust": 8.55
  },
  "rain": {
    "1h": 0.64
  },
  "clouds": {
    "all": 100
  },
  "dt": 1780728397,
  "sys": {
    "country": "CN",
    "sunrise": 1780692395,
    "sunset": 1780745983
  },
  "timezone": 28800,
  "id": 1816670,
  "name": "Beijing",
  "cod": 200
}