{
  "coord": {
    "lon": 31.0292,
    "lat": -29.8579
  },
  "weather": [
    {
      "id": 800,
      "main": "Clear",
      "description": "clear sky",
      "icon": "01d"
    }
  ],
  "base": "stations",
  "main": {
    "temp": 26.41,
    "feels_like": 26.41,
    "temp_min": 22.82,
    "temp_max": 26.41,
    "pressure": 1017,
    "humidity": 34,
    "sea_level": 1017,
    "grnd_level": 1015
  },
  "visibility": 10000,
  "wind": {
    "speed": 0.45,
    "deg": 5,
    "gust": 1.34
  },
  "clouds": {
    "all": 0
  },
  "dt": 1782633241,
  "sys": {
    "type": 2,
    "id": 2104340,
    "country": "ZA",
    "sunrise": 1782622314,
    "sunset": 1782659163
  },
  "timezone": 7200,
  "id": 1007311,
  "name": "Durban",
  "cod": 200
}