{
  "coord": {
    "lon": -118.2437,
    "lat": 34.0522
  },
  "weather": [
    {
      "id": 804,
      "main": "Clouds",
      "description": "overcast clouds",
      "icon": "04n"
    }
  ],
  "base": "stations",
  "main": {
    "temp": 15.23,
    "feels_like": 14.77,
    "temp_min": 14.19,
    "temp_max": 15.92,
    "pressure": 1014,
    "humidity": 75,
    "sea_level": 1014,
    "grnd_level": 995
  },
  "visibility": 10000,
  "wind": {
    "speed": 2.18,
    "deg": 232,
    "gust": 2.33
  },
  "clouds": {
    "all": 99
  },
  "dt": 1780041600,
  "sys": {
    "type": 2,
    "id": 2075946,
    "country": "US",
    "sunrise": 1780058629,
    "sunset": 1780109840
  },
  "timezone": -25200,
  "id": 5368361,
  "name": "Los Angeles",
  "cod": 200
}