{
  "coord": {
    "lon": 37.6156,
    "lat": 55.7522
  },
  "weather": [
    {
      "id": 804,
      "main": "Clouds",
      "description": "overcast clouds",
      "icon": "04d"
    }
  ],
  "base": "stations",
  "main": {
    "temp": 14.75,
    "feels_like": 14.08,
    "temp_min": 14.75,
    "temp_max": 14.75,
    "pressure": 1008,
    "humidity": 69,
    "sea_level": 1008,
    "grnd_level": 989
  },
  "visibility": 10000,
  "wind": {
    "speed": 4.52,
    "deg": 231,
    "gust": 7.42
  },
  "clouds": {
    "all": 90
  },
  "dt": 1781686551,
  "sys": {
    "country": "RU",
    "sunrise": 1781657060,
    "sunset": 1781720190
  },
  "timezone": 10800,
  "id": 524901,
  "name": "Moscow",
  "cod": 200
}