{
  "coord": {
    "lon": 116.3972,
    "lat": 39.9075
  },
  "weather": [
    {
      "id": 804,
      "main": "Clouds",
      "description": "overcast clouds",
      "icon": "04d"
    }
  ],
  "base": "stations",
  "main": {
    "temp": -5.06,
    "feels_like": -7.39,
    "temp_min": -5.06,
    "temp_max": -5.06,
    "pressure": 1035,
    "humidity": 14,
    "sea_level": 1035,
    "grnd_level": 1029
  },
  "visibility": 10000,
  "wind": {
    "speed": 1.43,
    "deg": 47,
    "gust": 0.88
  },
  "clouds": {
    "all": 100
  },
  "dt": 1770354991,
  "sys": {
    "type": 1,
    "id": 9609,
    "country": "CN",
    "sunrise": 1770333503,
    "sunset": 1770370713
  },
  "timezone": 28800,
  "id": 1816670,
  "name": "Beijing",
  "cod": 200
}