{
  "coord": {
    "lon": -2.0981,
    "lat": 57.1437
  },
  "weather": [
    {
      "id": 804,
      "main": "Clouds",
      "description": "overcast clouds",
      "icon": "04d"
    }
  ],
  "base": "stations",
  "main": {
    "temp": 17.33,
    "feels_like": 17.63,
    "temp_min": 17.33,
    "temp_max": 19.19,
    "pressure": 1017,
    "humidity": 96,
    "sea_level": 1017,
    "grnd_level": 1011
  },
  "visibility": 10000,
  "wind": {
    "speed": 1.22,
    "deg": 195,
    "gust": 1.4
  },
  "clouds": {
    "all": 100
  },
  "dt": 1783492398,
  "sys": {
    "type": 2,
    "id": 2031790,
    "country": "GB",
    "sunrise": 1783481104,
    "sunset": 1783544485
  },
  "timezone": 3600,
  "id": 2657832,
  "name": "Aberdeen",
  "cod": 200
}