{
  "coord": {
    "lon": -0.3833,
    "lat": 52.7667
  },
  "weather": [
    {
      "id": 803,
      "main": "Clouds",
      "description": "broken clouds",
      "icon": "04d"
    }
  ],
  "base": "stations",
  "main": {
    "temp": 21.52,
    "feels_like": 21.71,
    "temp_min": 21.05,
    "temp_max": 22.14,
    "pressure": 1021,
    "humidity": 76,
    "sea_level": 1021,
    "grnd_level": 1016
  },
  "visibility": 10000,
  "wind": {
    "speed": 3.36,
    "deg": 160,
    "gust": 4.93
  },
  "clouds": {
    "all": 56
  },
  "dt": 1782201147,
  "sys": {
    "type": 2,
    "id": 2111237,
    "country": "GB",
    "sunrise": 1782185834,
    "sunset": 1782246605
  },
  "timezone": 3600,
  "id": 2655099,
  "name": "Bourne",
  "cod": 200
}