{
  "coord": {
    "lon": 37.6156,
    "lat": 55.7522
  },
  "weather": [
    {
      "id": 803,
      "main": "Clouds",
      "description": "broken clouds",
      "icon": "04d"
    }
  ],
  "base": "stations",
  "main": {
    "temp": 1.94,
    "feels_like": -2.29,
    "temp_min": 1.88,
    "temp_max": 3.24,
    "pressure": 1019,
    "humidity": 74,
    "sea_level": 1019,
    "grnd_level": 1000
  },
  "visibility": 10000,
  "wind": {
    "speed": 4.64,
    "deg": 276,
    "gust": 12.48
  },
  "clouds": {
    "all": 79
  },
  "dt": 1773119279,
  "sys": {
    "type": 2,
    "id": 2000314,
    "country": "RU",
    "sunrise": 1773115121,
    "sunset": 1773156079
  },
  "timezone": 10800,
  "id": 524901,
  "name": "Moscow",
  "cod": 200
}