{
  "coord": {
    "lon": 28.0436,
    "lat": -26.2023
  },
  "weather": [
    {
      "id": 500,
      "main": "Rain",
      "description": "light rain",
      "icon": "10d"
    }
  ],
  "base": "stations",
  "main": {
    "temp": 13.34,
    "feels_like": 13.26,
    "temp_min": 12.63,
    "temp_max": 13.8,
    "pressure": 1013,
    "humidity": 97,
    "sea_level": 1013,
    "grnd_level": 826
  },
  "visibility": 10000,
  "wind": {
    "speed": 0.45,
    "deg": 253,
    "gust": 3.13
  },
  "rain": {
    "1h": 0.51
  },
  "clouds": {
    "all": 54
  },
  "dt": 1777962112,
  "sys": {
    "type": 2,
    "id": 2005686,
    "country": "ZA",
    "sunrise": 1777955610,
    "sunset": 1777995329
  },
  "timezone": 7200,
  "id": 993800,
  "name": "Johannesburg",
  "cod": 200
}