{
  "coord": {
    "lon": -2.5967,
    "lat": 51.4552
  },
  "weather": [
    {
      "id": 741,
      "main": "Fog",
      "description": "fog",
      "icon": "50n"
    }
  ],
  "base": "stations",
  "main": {
    "temp": 4.24,
    "feels_like": 0.08,
    "temp_min": 3.93,
    "temp_max": 5.25,
    "pressure": 996,
    "humidity": 97,
    "sea_level": 996,
    "grnd_level": 988
  },
  "visibility": 250,
  "wind": {
    "speed": 5.66,
    "deg": 100
  },
  "clouds": {
    "all": 100
  },
  "dt": 1769663332,
  "sys": {
    "type": 2,
    "id": 2001409,
    "country": "GB",
    "sunrise": 1769673194,
    "sunset": 1769705612
  },
  "timezone": 0,
  "id": 2654675,
  "name": "Bristol",
  "cod": 200
}