{
  "coord": {
    "lon": -118.2437,
    "lat": 34.0522
  },
  "weather": [
    {
      "id": 804,
      "main": "Clouds",
      "description": "overcast clouds",
      "icon": "04n"
    }
  ],
  "base": "stations",
  "main": {
    "temp": 13.57,
    "feels_like": 13.25,
    "temp_min": 12.42,
    "temp_max": 14.8,
    "pressure": 1013,
    "humidity": 87,
    "sea_level": 1013,
    "grnd_level": 993
  },
  "visibility": 10000,
  "wind": {
    "speed": 3.6,
    "deg": 240
  },
  "clouds": {
    "all": 100
  },
  "dt": 1769229443,
  "sys": {
    "type": 2,
    "id": 2075946,
    "country": "US",
    "sunrise": 1769180121,
    "sunset": 1769217242
  },
  "timezone": -28800,
  "id": 5368361,
  "name": "Los Angeles",
  "cod": 200
}